{
  "status": 200,
  "data": [
    {
      "qid": 0,
      "time": 5,
      "title": "员工离职多久后通知人员工离职多久后通知人员工离职久后通知人力资源部？(单选题)",
      "type": 0,
      "options": [
        {
          "mark": "A",
          "cont": "当天通知"
        },
        {
          "mark": "B",
          "cont": "隔天通知隔天通隔隔天通知隔天通知隔天通知隔天通知隔天通知隔天通知隔天通知隔天通知"
        },
        {
          "mark": "C",
          "cont": "每月15日通知"
        },
        {
          "mark": "D",
          "cont": "每月月底通知"
        }
      ],
      "remark": {
        "agree": 1,
        "against": 3,
        "reported": 4
      }
    },
    {
      "qid": 1,
      "time": 11,
      "title": "用人单位招用劳动者时不得有以下哪种行为？(多选题)",
      "type": 1,
      "options": [
        {
          "mark": "A",
          "cont": "扣押劳动者的居民身份证"
        },
        {
          "mark": "B",
          "cont": "要求劳动者提供担保"
        },
        {
          "mark": "C",
          "cont": "以各种名义收取财物"
        },
        {
          "mark": "D",
          "cont": "了解劳动者相关情况"
        }
      ],
      "remark": {
        "agree": 12,
        "against": 25,
        "reported": 0
      }
    },
    {
      "qid": 2,
      "time": 15,
      "title": "国家法律规定劳动者每日工作时间不得超过()？(单选题)",
      "type": 0,
      "options": [
        {
          "mark": "A",
          "cont": "6小时"
        },
        {
          "mark": "B",
          "cont": "7小时"
        },
        {
          "mark": "C",
          "cont": "8小时"
        },
        {
          "mark": "D",
          "cont": "12小时"
        }
      ],
      "remark": {
        "agree": 2,
        "against": 5,
        "reported": 6
      }
    },
    {
      "qid": 0,
      "time": 20,
      "title": "员工离职多久后通知人员工离职多久后通知人员工离职久后通知人力资源部？(单选题)",
      "type": 0,
      "options": [
        {
          "mark": "A",
          "cont": "当天通知"
        },
        {
          "mark": "B",
          "cont": "隔天通知隔天通隔隔天通知隔天通知隔天通知隔天通知隔天通知隔天通知隔天通知隔天通知"
        },
        {
          "mark": "C",
          "cont": "每月15日通知"
        },
        {
          "mark": "D",
          "cont": "每月月底通知"
        }
      ],
      "remark": {
        "agree": 1,
        "against": 3,
        "reported": 4
      }
    },
    {
      "qid": 1,
      "time": 18,
      "title": "用人单位招用劳动者时不得有以下哪种行为？(多选题)",
      "type": 1,
      "options": [
        {
          "mark": "A",
          "cont": "扣押劳动者的居民身份证"
        },
        {
          "mark": "B",
          "cont": "要求劳动者提供担保"
        },
        {
          "mark": "C",
          "cont": "以各种名义收取财物"
        },
        {
          "mark": "D",
          "cont": "了解劳动者相关情况"
        }
      ],
      "remark": {
        "agree": 12,
        "against": 25,
        "reported": 0
      }
    },
    {
      "qid": 2,
      "time": 15,
      "title": "国家法律规定劳动者每日工作时间不得超过()？(单选题)",
      "type": 0,
      "options": [
        {
          "mark": "A",
          "cont": "6小时"
        },
        {
          "mark": "B",
          "cont": "7小时"
        },
        {
          "mark": "C",
          "cont": "8小时"
        },
        {
          "mark": "D",
          "cont": "12小时"
        }
      ],
      "remark": {
        "agree": 2,
        "against": 5,
        "reported": 6
      }
    }
  ]
}